{
  "problem_id": "3Tree1",
  "total_events": 111,
  "test_result": {
    "final_score": 100,
    "test_passed": true,
    "passed_tests": 4,
    "total_tests": 4,
    "test_attempts": 1,
    "first_pass_attempt": 1,
    "test_success": true,
    "test_details": "[TEST] 正常二叉树\r\n[PASS] 正常二叉树\r\n[TEST] 单节点树\r\n[PASS] 单节点树\r\n[TEST] 空树\r\n[PASS] 空树\r\n[TEST] 只有左子树\r\n[PASS] 只有左子树\r\n[RESULT] 4/4 tests passed\r\n[SCORE] 100\r\n",
    "test_timestamp": 1764062870199
  },
  "time_analysis": {
    "total_duration_seconds": 777253.42,
    "total_duration_formatted": "215小时54分13秒",
    "active_duration_seconds": 862.02,
    "first_load_time": "2025-11-25 17:21:37",
    "actual_start_time": "2025-11-25 17:23:17",
    "actual_start_timestamp": 1764062597483,
    "last_event_time": "2025-12-04 17:15:51",
    "effective_duration_seconds": 777153.54,
    "effective_duration_formatted": "215小时52分33秒",
    "load_to_first_run_seconds": 237.54,
    "first_run_to_pass_seconds": 135.09,
    "pause_count": 2,
    "longest_pause_seconds": 442533.45,
    "invalid_load_count": 1
  },
  "edit_behavior": {
    "total_edits": 73,
    "type_count": 32,
    "ime_input_count": 0,
    "paste_insert_count": 5,
    "paste_replace_count": 7,
    "delete_count": 18,
    "undo_redo_count": 0,
    "other_edit_count": 11,
    "paste_ratio": 0.1644,
    "total_chars_added": 240,
    "total_chars_deleted": 58,
    "large_pastes": []
  },
  "execution": {
    "run_count": 4,
    "test_count": 1,
    "successful_runs": 0,
    "compile_errors": 4,
    "compile_error_details": [
      {
        "timestamp": 1764062745346,
        "error_message": "'ldepth' was not declared in this scope\nrequest for member 'left' in 'root', which is of pointer type 'TreeNode*' (maybe you meant to use '->' ?)\n'rdepth' was not declared in this scope\nrequest for member 'right' in 'root', which is of pointer type 'TreeNode*' (maybe you meant to use '->' ?)\nconverting to execution character set: Illegal byte sequence",
        "time": "2025-11-25 17:25:45"
      },
      {
        "timestamp": 1764062764163,
        "error_message": "'ldepth' was not declared in this scope\n'rdepth' was not declared in this scope\nconverting to execution character set: Illegal byte sequence",
        "time": "2025-11-25 17:26:04"
      },
      {
        "timestamp": 1764062777579,
        "error_message": "converting to execution character set: Illegal byte sequence",
        "time": "2025-11-25 17:26:17"
      },
      {
        "timestamp": 1764062803224,
        "error_message": "converting to execution character set: Illegal byte sequence",
        "time": "2025-11-25 17:26:43"
      }
    ],
    "run_timeouts": 0,
    "debug_sessions": 0,
    "debug_steps": 0,
    "breakpoint_adds": 0,
    "breakpoint_removes": 0,
    "debug_expr_evals": 0,
    "debug_usage_ratio": 0.0
  },
  "lifecycle": {
    "load_count": 5,
    "save_count": 8,
    "has_audio": true,
    "audio_record_count": 4,
    "audio_play_count": 2
  },
  "suspicious_behaviors": [],
  "learning_strategy": {
    "strategy_type": "平衡型",
    "proficiency_score": 70
  },
  "metadata": {
    "student_id": "2024151610028_严天浩",
    "problem_id": "3Tree1",
    "analysis_time": "2026-01-12 12:30:08",
    "history_events_count": 111,
    "has_test_result_file": true
  },
  "ai_analysis": {
    "knowledge_points_analysis": [
      {
        "knowledge_point": "二叉树的递归定义与遍历",
        "mastery_level": "精通",
        "mastery_score": 95,
        "is_weak": false,
        "evidence_from_history": [
          "最终代码正确实现了递归计算二叉树高度的逻辑。",
          "代码结构清晰，直接应用了二叉树的递归定义：高度 = 1 + max(左子树高度, 右子树高度)。",
          "通过了所有测试用例，包括空树、单节点树和正常二叉树。"
        ],
        "specific_errors": [],
        "improvement_suggestions": [
          "继续练习其他基于递归的二叉树问题，如前序、中序、后序遍历，以及查找节点等。"
        ]
      },
      {
        "knowledge_point": "C++ 指针与成员访问",
        "mastery_level": "一般",
        "mastery_score": 60,
        "is_weak": true,
        "evidence_from_history": [
          "在timestamp=1764062745346的compile_error中，出现了'request for member 'left' in 'root', which is of pointer type 'TreeNode*' (maybe you meant to use '->' ?)'",
          "在timestamp=1764062754886和1764062757356的edit事件中，学生将'.'修改为'->'来访问指针指向的成员。",
          "这表明学生在访问指针指向的结构体成员时，混淆了点运算符（.）和箭头运算符（->）。"
        ],
        "specific_errors": [
          "在访问指针 `root` 的 `left` 和 `right` 成员时，错误地使用了点运算符 `.` 而非箭头运算符 `->`。"
        ],
        "improvement_suggestions": [
          "加强C++中指针和对象/结构体成员访问的练习，区分 `.` 和 `->` 的使用场景。",
          "理解指针的本质是存储内存地址，访问其指向的内容需要使用解引用操作符（*）或箭头运算符（->）。"
        ]
      },
      {
        "knowledge_point": "C++ 变量声明与作用域",
        "mastery_level": "一般",
        "mastery_score": 55,
        "is_weak": true,
        "evidence_from_history": [
          "在timestamp=1764062764163的compile_error中，出现了'ldepth' was not declared in this scope' 和 'rdepth' was not declared in this scope'。",
          "在timestamp=1764062767122和1764062771321的edit事件中，学生在 `ldepth` 和 `rdepth` 前添加了 `int` 关键字进行声明。",
          "这表明学生在递归调用中，忘记了声明局部变量 `ldepth` 和 `rdepth`。"
        ],
        "specific_errors": [
          "在递归函数 `maxDepth` 中，局部变量 `ldepth` 和 `rdepth` 在使用前未声明，导致编译错误。"
        ],
        "improvement_suggestions": [
          "在编写函数内部变量时，务必确保在使用前已正确声明其类型。",
          "理解变量的作用域规则，确保变量在声明的范围内可用。"
        ]
      },
      {
        "knowledge_point": "递归函数设计",
        "mastery_level": "良好",
        "mastery_score": 80,
        "is_weak": false,
        "evidence_from_history": [
          "学生能够正确设计递归的终止条件（`root == nullptr` 返回0）。",
          "能够正确地将问题分解为子问题（递归调用 `maxDepth` 处理左右子树）。",
          "最终代码逻辑正确，能够计算出二叉树的高度。"
        ],
        "specific_errors": [],
        "improvement_suggestions": [
          "继续练习更复杂的递归问题，如斐波那契数列、全排列、组合等，以加深对递归思想的理解。"
        ]
      },
      {
        "knowledge_point": "C++ 编译错误处理",
        "mastery_level": "良好",
        "mastery_score": 85,
        "is_weak": false,
        "evidence_from_history": [
          "学生在遇到编译错误（如timestamp=1764062745346, 1764062764163, 1764062777579）后，能够通过修改代码来解决问题。",
          "学生能够根据错误信息（如'未声明的标识符'，'指针成员访问错误'）定位问题并进行修正。",
          "最终代码能够成功编译并运行通过所有测试。"
        ],
        "specific_errors": [],
        "improvement_suggestions": [
          "学习更有效地利用编译器提供的错误信息，例如理解错误类型和行号，可以更快地定位问题。",
          "掌握使用IDE的调试功能（如断点、单步执行）来辅助排查逻辑错误。"
        ]
      }
    ],
    "weak_knowledge_points_summary": [
      {
        "knowledge_point": "C++ 指针与成员访问",
        "severity": "严重",
        "priority": "高"
      },
      {
        "knowledge_point": "C++ 变量声明与作用域",
        "severity": "严重",
        "priority": "高"
      }
    ],
    "debugging_ability": {
      "score": 70,
      "level": "良好",
      "error_recognition_ability": "能够识别并理解编译错误信息，特别是关于未声明变量和指针访问的错误。",
      "error_fixing_efficiency": "在遇到编译错误后，通常需要2-3次尝试（编辑-保存-运行）才能完全解决。",
      "debugging_strategy": "主要依赖于编译器的错误提示和测试用例的反馈，通过修改代码来解决问题。缺乏系统性的调试工具使用。",
      "evidence_from_history": "学生在遇到编译错误后，会进行多次编辑和运行操作，直到错误消失。例如，指针访问错误和变量声明错误都经过了多次修改和尝试。"
    },
    "code_evolution_analysis": {
      "total_iterations": 4,
      "improvement_pattern": "试错与修正型",
      "key_changes": [
        "初始状态：代码框架基本完成，但存在指针访问错误和变量声明错误。",
        "第一次编译错误：暴露了指针访问问题（'.' vs '->'）。",
        "第二次编译错误：暴露了变量声明问题（`ldepth`, `rdepth` 未声明）。",
        "最终状态：所有编译错误解决，逻辑正确，通过测试。"
      ],
      "learning_curve": "学生在遇到错误后能够学习并修正，显示出一定的学习能力，但初始代码存在基础性错误。",
      "independence_assessment": "中等。学生能够独立完成大部分代码逻辑，但在基础语法（指针访问、变量声明）上存在困惑，可能需要查阅资料或参考示例。"
    },
    "code_quality": {
      "correctness": {
        "score": 90,
        "comment": "最终代码逻辑正确，通过了所有测试用例。"
      },
      "time_complexity": {
        "actual": "O(N)",
        "optimal": "O(N)",
        "is_optimal": true,
        "comment": "递归遍历二叉树所有节点，时间复杂度为O(N)，其中N为节点数，达到最优。"
      },
      "space_complexity": {
        "actual": "O(H)",
        "optimal": "O(H)",
        "is_optimal": true,
        "comment": "递归调用栈深度最大为树的高度H，空间复杂度为O(H)，达到最优。"
      },
      "readability": {
        "score": 75,
        "comment": "代码结构清晰，命名规范，但缺少对递归逻辑的详细注释。"
      },
      "code_style": {
        "score": 70,
        "comment": "整体代码风格较好，缩进和格式基本统一，但部分地方（如`ldepth>rdepth?ldepth:rdepth`）可以考虑使用`std::max`提高可读性。"
      }
    },
    "learning_process_assessment": {
      "problem_solving_strategy": "试错与修正",
      "strategy_description": "学生首先尝试实现核心逻辑，然后通过编译和测试来发现问题，并根据错误信息进行修正。这种方法在解决基础语法问题时有效，但可能效率不高。",
      "independence_level": "中等",
      "independence_evidence": "学生独立编写了递归的核心逻辑，但多次出现基础语法错误，表明在某些基础概念上可能需要加强理解或参考。",
      "time_management": "总学习时长和编辑次数表明学生投入了足够的时间进行尝试和修改。",
      "focus_level": "操作历史显示学生在遇到错误后会持续进行修改和运行，表明其专注度较高，致力于解决问题。"
    },
    "overall_assessment": {
      "mastery_percentage": 78,
      "mastery_level": "良好",
      "grade_recommendation": "B",
      "confidence_level": "高",
      "confidence_reason": "分析基于完整的操作历史记录，包括代码修改、编译错误和测试结果，证据充分。",
      "readiness_for_next_topic": false,
      "readiness_reason": "指针访问和变量声明的基础知识掌握不牢固，建议在继续学习新内容前巩固这些基础概念。",
      "key_strengths": [
        "能够理解并实现二叉树的递归定义。",
        "学习态度积极，愿意通过反复尝试解决问题。",
        "能够从编译错误中学习并修正代码。"
      ],
      "key_weaknesses": [
        "C++ 指针成员访问（`.` vs `->`）和变量声明基础概念不牢固。",
        "调试策略偏向于试错，缺乏系统性调试工具的使用。",
        "代码可读性方面，可以进一步优化（如使用`std::max`）。"
      ],
      "priority_improvements": [
        "加强C++指针和变量作用域的基础知识学习和练习。",
        "学习使用IDE的调试器来辅助代码调试。",
        "在编写代码时，注意检查变量声明和指针访问的正确性。"
      ]
    },
    "metadata": {
      "analysis_timestamp": "2024-07-29 10:00:00",
      "has_complete_history": true,
      "history_event_count": 111,
      "analysis_quality": "深度分析"
    }
  }
}