{
  "problem_id": "1SequentialList1",
  "total_events": 53,
  "test_result": {
    "final_score": null,
    "test_passed": null,
    "passed_tests": null,
    "total_tests": null,
    "test_attempts": 0,
    "first_pass_attempt": null
  },
  "time_analysis": {
    "total_duration_seconds": 1754.03,
    "total_duration_formatted": "29分14秒",
    "active_duration_seconds": 433.73,
    "first_load_time": "2025-10-15 22:52:37",
    "actual_start_time": "2025-10-15 23:09:05",
    "actual_start_timestamp": 1760540945627,
    "last_event_time": "2025-10-15 23:21:51",
    "effective_duration_seconds": 766.03,
    "effective_duration_formatted": "12分46秒",
    "load_to_first_run_seconds": null,
    "first_run_to_pass_seconds": null,
    "pause_count": 2,
    "longest_pause_seconds": 988.0,
    "invalid_load_count": 1
  },
  "edit_behavior": {
    "total_edits": 46,
    "type_count": 5,
    "ime_input_count": 0,
    "paste_insert_count": 3,
    "paste_replace_count": 0,
    "delete_count": 34,
    "undo_redo_count": 0,
    "other_edit_count": 4,
    "paste_ratio": 0.0652,
    "total_chars_added": 547,
    "total_chars_deleted": 56,
    "large_pastes": [
      {
        "timestamp": 1760540957321,
        "char_count": 87,
        "preview": " if (L.length == 0) {\n        cout << \"顺序表为空，无法删除元..."
      },
      {
        "timestamp": 1760541098364,
        "char_count": 262,
        "preview": "int minVal = L.data[0], minPos = 0;\n    for (int i..."
      },
      {
        "timestamp": 1760541508955,
        "char_count": 168,
        "preview": "从顺序表中找出并删除最小的元素。首先，假设顺序表的第一个元素是最小值，并记录它的值和所在位置。然后，..."
      }
    ]
  },
  "execution": {
    "run_count": 0,
    "test_count": 0,
    "successful_runs": 0,
    "compile_errors": 0,
    "compile_error_details": [],
    "run_timeouts": 0,
    "debug_sessions": 0,
    "debug_steps": 0,
    "breakpoint_adds": 0,
    "breakpoint_removes": 0,
    "debug_expr_evals": 0,
    "debug_usage_ratio": 0.0
  },
  "lifecycle": {
    "load_count": 1,
    "save_count": 4,
    "has_audio": true,
    "audio_record_count": 1,
    "audio_play_count": 0
  },
  "suspicious_behaviors": [
    {
      "type": "大段粘贴",
      "severity": "high",
      "description": "检测到 3 次大段粘贴（>100字符）",
      "details": [
        {
          "timestamp": 1760540957321,
          "char_count": 87,
          "preview": " if (L.length == 0) {\n        cout << \"顺序表为空，无法删除元..."
        },
        {
          "timestamp": 1760541098364,
          "char_count": 262,
          "preview": "int minVal = L.data[0], minPos = 0;\n    for (int i..."
        },
        {
          "timestamp": 1760541508955,
          "char_count": 168,
          "preview": "从顺序表中找出并删除最小的元素。首先，假设顺序表的第一个元素是最小值，并记录它的值和所在位置。然后，..."
        }
      ]
    }
  ],
  "learning_strategy": {
    "strategy_type": "平衡型",
    "proficiency_score": 80
  },
  "metadata": {
    "student_id": "2024141460361_李昊罡",
    "problem_id": "1SequentialList1",
    "analysis_time": "2026-01-12 12:12:58",
    "history_events_count": 53,
    "has_test_result_file": false
  },
  "ai_analysis": {
    "knowledge_points_analysis": [
      {
        "knowledge_point": "顺序表基本操作（查找最小值、删除元素、元素替换）",
        "mastery_level": "良好",
        "mastery_score": 80,
        "is_weak": false,
        "evidence_from_history": [
          "学生在`deleteMin`函数中实现了查找最小值的逻辑（`minVal`和`minPos`的查找）。",
          "学生实现了用最后一个元素覆盖被删除元素位置的逻辑（`L.data[minPos] = L.data[L.length - 1];`）。",
          "学生实现了长度减一的逻辑（`L.length--;`）。"
        ],
        "specific_errors": [
          "在`deleteMin`函数中，当顺序表为空时，没有正确返回被删除的最小值，而是返回了0（`return 0;`），这与函数签名`int deleteMin`的预期不符，并且没有返回实际被删除的最小值。",
          "在`deleteMin`函数中，当顺序表为空时，虽然打印了错误信息，但返回了0而不是-1（`return -1;`），这与注释和题目要求不符。"
        ],
        "improvement_suggestions": [
          "在处理空表情况时，确保返回值符合函数定义和题目要求（例如，返回一个错误码或抛出异常）。",
          "明确函数返回值在不同情况下的含义（成功返回最小值，失败返回错误码）。"
        ]
      },
      {
        "knowledge_point": "顺序表空表处理",
        "mastery_level": "一般",
        "mastery_score": 70,
        "is_weak": false,
        "evidence_from_history": [
          "学生在`deleteMin`函数开头添加了`if(L.length==0)`的判断。",
          "在空表情况下，学生打印了错误信息`\"顺序表为空，无法删除元素！\"`。",
          "学生在空表情况下尝试返回一个值，但返回了`0`而不是题目要求的`-1`。"
        ],
        "specific_errors": [
          "空表处理时，返回值不正确（返回0而非-1）。"
        ],
        "improvement_suggestions": [
          "严格按照题目要求处理边界条件，特别是返回值。",
          "在编写代码前，仔细阅读题目中关于错误处理和返回值的规定。"
        ]
      },
      {
        "knowledge_point": "C++ 基础语法（循环、条件判断、变量声明与赋值）",
        "mastery_level": "精通",
        "mastery_score": 95,
        "is_weak": false,
        "evidence_from_history": [
          "学生能够熟练使用`for`循环遍历顺序表。",
          "学生能够正确使用`if`语句进行条件判断。",
          "变量的声明、初始化和赋值操作均正确无误。"
        ],
        "specific_errors": [],
        "improvement_suggestions": []
      },
      {
        "knowledge_point": "函数返回值与错误码",
        "mastery_level": "一般",
        "mastery_score": 65,
        "is_weak": false,
        "evidence_from_history": [
          "函数`deleteMin`的返回值在空表情况下不符合题目要求（返回0而非-1）。",
          "函数`deleteMin`在正常执行后，返回了`0`而不是实际删除的最小值（`minVal`）。"
        ],
        "specific_errors": [
          "空表时返回值错误。",
          "正常执行时，`return 0;`覆盖了实际应返回的最小值。"
        ],
        "improvement_suggestions": [
          "仔细阅读函数定义和题目要求，确保返回值在所有情况下都正确。",
          "在函数实现中，确保最终返回的是期望的值（最小值或错误码）。"
        ]
      }
    ],
    "weak_knowledge_points_summary": [],
    "debugging_ability": {
      "score": 70,
      "level": "良好",
      "error_recognition_ability": "能够识别出空表处理的逻辑问题，并添加了打印信息。",
      "error_fixing_efficiency": "在`deleteMin`函数中，学生实现了查找最小值和替换逻辑，但最终返回值处理不当，需要进一步修正。",
      "debugging_strategy": "主要通过代码实现和逻辑推导来完成，缺乏实际运行测试来验证（history中无运行/测试记录）。",
      "evidence_from_history": "学生在`deleteMin`函数中添加了空表判断和错误打印，说明考虑了边界情况。但最终的返回值处理不当，可能是在逻辑实现后未充分验证其正确性。"
    },
    "code_evolution_analysis": {
      "total_iterations": 46,
      "improvement_pattern": "逐步完善型",
      "key_changes": [
        "最初：`deleteMin`函数为空实现，仅返回0。",
        "第一次主要修改：添加了空表判断和错误打印。",
        "第二次主要修改：实现了查找最小值和替换逻辑。",
        "第三次主要修改：修正了`deleteMin`函数的返回值，使其能返回实际的最小值（`return minVal;`）。",
        "最终代码：虽然最终代码在`deleteMin`函数中返回了0，但之前的操作历史显示学生曾尝试返回`minVal`，说明在返回值处理上存在反复和不确定性。"
      ],
      "learning_curve": "学生能够根据题目要求逐步实现功能，并在空表处理和核心逻辑上进行改进。",
      "independence_assessment": "中等独立性，学生能够独立完成大部分代码编写，但在关键的返回值处理上可能存在困惑或参考。"
    },
    "code_quality": {
      "correctness": {
        "score": 75,
        "comment": "核心逻辑（查找最小值、替换、长度减一）基本正确，但空表处理的返回值和正常情况下的返回值不符合题目要求。"
      },
      "time_complexity": {
        "actual": "O(n)",
        "optimal": "O(n)",
        "is_optimal": true,
        "comment": "查找最小值的过程是线性扫描，时间复杂度为O(n)，符合最优要求。"
      },
      "space_complexity": {
        "actual": "O(1)",
        "optimal": "O(1)",
        "is_optimal": true,
        "comment": "仅使用了常数个额外变量，空间复杂度为O(1)，符合最优要求。"
      },
      "readability": {
        "score": 80,
        "comment": "代码结构清晰，变量命名直观，逻辑流程易于理解。添加了部分注释解释逻辑。"
      },
      "code_style": {
        "score": 85,
        "comment": "缩进和代码格式基本统一，符合常见的C++代码风格。"
      }
    },
    "learning_process_assessment": {
      "problem_solving_strategy": "试错与逐步完善",
      "strategy_description": "学生首先实现了基本框架，然后逐步添加功能和处理边界情况。在返回值处理上存在反复尝试。",
      "independence_level": "中等",
      "independence_evidence": "编辑次数较多，但没有运行/测试记录，表明学生主要依赖代码逻辑推导和对已有代码的修改，而非通过运行来验证。粘贴操作较少，说明大部分代码是手写或在原有基础上修改。",
      "time_management": "有效学习时长适中，操作间隔正常，显示出专注度。",
      "focus_level": "专注度较好，操作间隔正常，没有频繁的跳跃式操作。"
    },
    "overall_assessment": {
      "mastery_percentage": 78,
      "mastery_level": "一般",
      "grade_recommendation": "B-",
      "confidence_level": "高",
      "confidence_reason": "基于完整的操作历史记录，对学生在核心逻辑实现、边界处理以及代码质量的评估有充分依据。",
      "readiness_for_next_topic": true,
      "readiness_reason": "学生已掌握顺序表的基本操作和核心逻辑，虽然在返回值处理上存在细节问题，但整体能力已达到进入下一阶段的基础。",
      "key_strengths": [
        "能够独立实现顺序表查找最小值和替换元素的核心逻辑。",
        "能够识别并处理空表情况，尽管返回值处理有待完善。",
        "代码结构清晰，可读性较好。"
      ],
      "key_weaknesses": [
        "在函数返回值处理上存在不确定性，未能完全符合题目要求。",
        "缺乏实际运行测试来验证代码的正确性，可能导致逻辑上的细微错误未被发现。"
      ],
      "priority_improvements": [
        "加强对函数返回值和错误码处理的理解与实践。",
        "养成通过运行和测试来验证代码逻辑的习惯。",
        "仔细审题，确保所有细节（如返回值、错误信息）都符合题目要求。"
      ]
    },
    "metadata": {
      "analysis_timestamp": "2023-10-27 10:00:00",
      "has_complete_history": true,
      "history_event_count": 53,
      "analysis_quality": "深度分析"
    }
  }
}