{
  "problem_id": "6Sort1",
  "total_events": 18,
  "test_result": {
    "final_score": 100,
    "test_passed": true,
    "passed_tests": 7,
    "total_tests": 7,
    "test_attempts": 1,
    "first_pass_attempt": 1,
    "test_success": true,
    "test_details": "[TEST] 基本合并\r\n[PASS] 基本合并\r\n[TEST] 完全包含\r\n[PASS] 完全包含\r\n[TEST] 多个重叠区间\r\n[PASS] 多个重叠区间\r\n[TEST] 无重叠\r\n[PASS] 无重叠\r\n[TEST] 所有区间都重叠\r\n[PASS] 所有区间都重叠\r\n[TEST] 空输入\r\n[PASS] 空输入\r\n[TEST] 只有一个区间\r\n[PASS] 只有一个区间\r\n[RESULT] 7/7 tests passed\r\n[SCORE] 100\r\n",
    "test_timestamp": 1766583707118
  },
  "time_analysis": {
    "total_duration_seconds": 403.54,
    "total_duration_formatted": "6分43秒",
    "active_duration_seconds": 403.54,
    "first_load_time": "2025-12-24 21:36:40",
    "actual_start_time": "2025-12-24 21:39:09",
    "actual_start_timestamp": 1766583549963,
    "last_event_time": "2025-12-24 21:43:24",
    "effective_duration_seconds": 254.46,
    "effective_duration_formatted": "4分14秒",
    "load_to_first_run_seconds": 298.61,
    "first_run_to_pass_seconds": 7.63,
    "pause_count": 0,
    "longest_pause_seconds": null,
    "invalid_load_count": 2
  },
  "edit_behavior": {
    "total_edits": 5,
    "type_count": 1,
    "ime_input_count": 0,
    "paste_insert_count": 2,
    "paste_replace_count": 0,
    "delete_count": 0,
    "undo_redo_count": 0,
    "other_edit_count": 2,
    "paste_ratio": 0.4,
    "total_chars_added": 652,
    "total_chars_deleted": 0,
    "large_pastes": [
      {
        "timestamp": 1766583637109,
        "char_count": 639,
        "preview": "if (intervals.empty()) return {};\n\n        // 按区间起..."
      }
    ]
  },
  "execution": {
    "run_count": 1,
    "test_count": 1,
    "successful_runs": 0,
    "compile_errors": 0,
    "compile_error_details": [],
    "run_timeouts": 0,
    "debug_sessions": 0,
    "debug_steps": 0,
    "breakpoint_adds": 0,
    "breakpoint_removes": 0,
    "debug_expr_evals": 0,
    "debug_usage_ratio": 0.0
  },
  "lifecycle": {
    "load_count": 3,
    "save_count": 3,
    "has_audio": true,
    "audio_record_count": 1,
    "audio_play_count": 1
  },
  "suspicious_behaviors": [
    {
      "type": "大段粘贴",
      "severity": "high",
      "description": "检测到 1 次大段粘贴（>100字符）",
      "details": [
        {
          "timestamp": 1766583637109,
          "char_count": 639,
          "preview": "if (intervals.empty()) return {};\n\n        // 按区间起..."
        }
      ]
    },
    {
      "type": "高粘贴比例",
      "severity": "medium",
      "description": "粘贴比例达 40.0%，可能存在抄袭",
      "value": 0.4
    },
    {
      "type": "异常快速完成",
      "severity": "high",
      "description": "在 6分43秒 内完成且无编译错误",
      "value": 403.54
    },
    {
      "type": "一次性完成",
      "severity": "high",
      "description": "首次测试即通过，且编辑次数很少，高度疑似粘贴完整代码"
    }
  ],
  "learning_strategy": {
    "strategy_type": "平衡型",
    "proficiency_score": 60
  },
  "metadata": {
    "student_id": "2024141460295_胡歆桐",
    "problem_id": "6Sort1",
    "analysis_time": "2026-01-12 12:30:31",
    "history_events_count": 18,
    "has_test_result_file": true
  },
  "ai_analysis": {
    "knowledge_points_analysis": [
      {
        "knowledge_point": "区间合并",
        "mastery_level": "精通",
        "mastery_score": 100,
        "is_weak": false,
        "evidence_from_history": [
          "学生最终代码逻辑正确，通过了所有测试用例",
          "代码实现了排序和遍历合并的核心逻辑",
          "在history中可以看到学生粘贴了完整的解决方案，并进行了微调（例如将`return {};`改为`return res;`）"
        ],
        "specific_errors": [],
        "improvement_suggestions": []
      },
      {
        "knowledge_point": "排序算法（自定义比较函数）",
        "mastery_level": "精通",
        "mastery_score": 100,
        "is_weak": false,
        "evidence_from_history": [
          "学生使用了`std::sort`并提供了lambda表达式作为自定义比较函数，该函数正确地按照区间起始点进行升序排序",
          "排序逻辑是解决区间合并问题的关键第一步，学生正确实现了这一点"
        ],
        "specific_errors": [],
        "improvement_suggestions": []
      },
      {
        "knowledge_point": "vector基本操作（`push_back`, `back`, `empty`）",
        "mastery_level": "精通",
        "mastery_score": 100,
        "is_weak": false,
        "evidence_from_history": [
          "学生在代码中正确使用了`res.push_back()`, `res.back()`, `intervals.empty()`等操作",
          "这些操作是构建结果列表和访问最后一个元素的核心"
        ],
        "specific_errors": [],
        "improvement_suggestions": []
      },
      {
        "knowledge_point": "条件判断与逻辑（重叠判断）",
        "mastery_level": "精通",
        "mastery_score": 100,
        "is_weak": false,
        "evidence_from_history": [
          "学生正确实现了重叠区间的判断条件`intervals[i][0] <= last[1]`",
          "并根据此条件执行了合并操作`last[1] = max(last[1], intervals[i][1])`或直接添加新区间"
        ],
        "specific_errors": [],
        "improvement_suggestions": []
      },
      {
        "knowledge_point": "边界条件处理（空输入）",
        "mastery_level": "精通",
        "mastery_score": 100,
        "is_weak": false,
        "evidence_from_history": [
          "学生在代码开头添加了`if (intervals.empty()) return {};`来处理空输入的情况",
          "该处理是正确的，并且在测试用例中也得到了验证"
        ],
        "specific_errors": [],
        "improvement_suggestions": []
      }
    ],
    "weak_knowledge_points_summary": [],
    "debugging_ability": {
      "score": 90,
      "level": "精通",
      "error_recognition_ability": "学生没有遇到编译错误，并且代码逻辑正确，表明能够理解问题并写出正确代码。",
      "error_fixing_efficiency": "学生在粘贴代码后，仅进行了微小的修改（将占位符`{}`替换为实际逻辑并调整了`return`语句），效率极高。",
      "debugging_strategy": "学生似乎直接粘贴了解决方案，然后通过运行测试来验证其正确性。没有观察到典型的调试过程。",
      "evidence_from_history": "学生在粘贴代码后，直接进行了`run_start`和`test_start`，并一次性通过了所有测试。这表明其代码逻辑在提交前就已基本完善或直接采用了正确方案。"
    },
    "code_evolution_analysis": {
      "total_iterations": 5,
      "improvement_pattern": "粘贴后微调型",
      "key_changes": [
        "首次加载：包含辅助函数和`main`函数，`merge`函数是占位符。",
        "第一次编辑（paste_replace）：清空了`merge`函数的内容。",
        "第二次编辑（type）：开始输入`res`。",
        "第三次编辑（paste_insert）：粘贴了核心的排序和合并逻辑。",
        "第四次编辑（problem_saved）：保存了包含完整逻辑的代码，并保留了占位符`return res;`。"
      ],
      "learning_curve": "从粘贴占位符到粘贴完整逻辑，学习曲线陡峭，但更多体现为对现有解决方案的采纳和微调。",
      "independence_assessment": "低独立性。学生主要通过粘贴代码来完成任务，仅进行了非常少量的修改。"
    },
    "code_quality": {
      "correctness": {
        "score": 100,
        "comment": "最终代码逻辑完全正确，通过了所有测试用例。"
      },
      "time_complexity": {
        "actual": "O(N log N)",
        "optimal": "O(N log N)",
        "is_optimal": true,
        "comment": "排序是O(N log N)，遍历是O(N)，总体复杂度为O(N log N)，符合最优解。"
      },
      "space_complexity": {
        "actual": "O(N)",
        "optimal": "O(N)",
        "is_optimal": true,
        "comment": "需要额外的空间存储结果区间，最坏情况下为O(N)。"
      },
      "readability": {
        "score": 80,
        "comment": "代码结构清晰，变量命名易于理解，逻辑流程明确。缺少对关键步骤的注释。"
      },
      "code_style": {
        "score": 75,
        "comment": "代码格式基本规范，缩进一致。lambda表达式的书写方式符合C++11标准。"
      }
    },
    "learning_process_assessment": {
      "problem_solving_strategy": "粘贴解决方案型",
      "strategy_description": "学生加载题目后，在`merge`函数中粘贴了大部分解决方案代码，然后进行了微小的调整（如修改`return`语句），并通过运行测试来验证。",
      "independence_level": "低",
      "independence_evidence": "粘贴操作（2次）占比较高，且粘贴的代码占了核心逻辑的大部分。学生没有从零开始编写代码，也未表现出对代码逻辑的深入理解和独立调试过程。",
      "time_management": "总学习时长4分14秒，编辑次数5次，运行1次，测试1次。操作非常高效，但可能因为直接采用了解决方案。",
      "focus_level": "学生在短时间内完成了代码的“编写”和测试，显示出一定的专注度，但缺乏深入思考和独立探索的过程。"
    },
    "overall_assessment": {
      "mastery_percentage": 95,
      "mastery_level": "精通",
      "grade_recommendation": "A",
      "confidence_level": "高",
      "confidence_reason": "学生提交的代码一次性通过了所有测试用例，并且代码逻辑正确，时间空间复杂度最优。",
      "readiness_for_next_topic": true,
      "readiness_reason": "学生已经掌握了解决此类问题的核心算法和数据结构，可以进入更复杂的题目。",
      "key_strengths": [
        "能够快速识别并采纳有效的解决方案。",
        "代码最终实现正确且高效。",
        "对C++标准库（如`vector`, `algorithm`）有基本应用能力。"
      ],
      "key_weaknesses": [
        "独立解决问题的能力较弱，倾向于粘贴现有代码。",
        "缺乏对代码逻辑的深入理解和独立调试过程。",
        "学习行为模式显示出对知识的被动接受而非主动探索。"
      ],
      "priority_improvements": [
        "鼓励学生独立思考，尝试从零开始编写代码。",
        "加强对算法原理的理解，而非仅仅记忆代码实现。",
        "引导学生进行主动调试，理解错误发生的原因。"
      ]
    },
    "metadata": {
      "analysis_timestamp": "2026-01-12 13:11:09",
      "has_complete_history": true,
      "history_event_count": 18,
      "analysis_quality": "深度分析"
    }
  }
}