{
  "problem_id": "3Tree4",
  "total_events": 53,
  "test_result": {
    "final_score": 100,
    "test_passed": true,
    "passed_tests": 9,
    "total_tests": 9,
    "test_attempts": 3,
    "first_pass_attempt": 3,
    "test_success": true,
    "test_details": "[TEST] 简单加法 a+b\r\n[PASS] 简单加法 a+b\r\n[TEST] 乘法优先级 a+b*c\r\n[PASS] 乘法优先级 a+b*c\r\n[TEST] 括号改变优先级 (a+b)*c\r\n[PASS] 括号改变优先级 (a+b)*c\r\n[TEST] 复杂表达式 (a+b)*c - d/e\r\n[PASS] 复杂表达式 (a+b)*c - d/e\r\n[TEST] 连续同优先级左结合 a/b/c\r\n[PASS] 连续同优先级左结合 a/b/c\r\n[TEST] 连续同优先级右结合 a-(b-c)\r\n[PASS] 连续同优先级右结合 a-(b-c)\r\n[TEST] 混合优先级和括号 (a-b)*(c+d)\r\n[PASS] 混合优先级和括号 (a-b)*(c+d)\r\n[TEST] 单操作数\r\n[PASS] 单操作数\r\n[TEST] 空树\r\n[PASS] 空树\r\n[RESULT] 9/9 tests passed\r\n[SCORE] 100\r\n",
    "test_timestamp": 1764594138805
  },
  "time_analysis": {
    "total_duration_seconds": 994.36,
    "total_duration_formatted": "16分34秒",
    "active_duration_seconds": 537.44,
    "first_load_time": "2025-12-01 20:59:38",
    "actual_start_time": "2025-12-01 20:59:38",
    "actual_start_timestamp": 1764593978075,
    "last_event_time": "2025-12-01 21:16:12",
    "effective_duration_seconds": 994.36,
    "effective_duration_formatted": "16分34秒",
    "load_to_first_run_seconds": -617.59,
    "first_run_to_pass_seconds": 160.67,
    "pause_count": 1,
    "longest_pause_seconds": 456.93,
    "invalid_load_count": 0
  },
  "edit_behavior": {
    "total_edits": 16,
    "type_count": 6,
    "ime_input_count": 0,
    "paste_insert_count": 2,
    "paste_replace_count": 1,
    "delete_count": 3,
    "undo_redo_count": 0,
    "other_edit_count": 4,
    "paste_ratio": 0.1875,
    "total_chars_added": 53,
    "total_chars_deleted": 3,
    "large_pastes": []
  },
  "execution": {
    "run_count": 5,
    "test_count": 3,
    "successful_runs": 4,
    "compile_errors": 0,
    "compile_error_details": [],
    "run_timeouts": 0,
    "debug_sessions": 0,
    "debug_steps": 0,
    "breakpoint_adds": 0,
    "breakpoint_removes": 0,
    "debug_expr_evals": 0,
    "debug_usage_ratio": 0.0
  },
  "lifecycle": {
    "load_count": 1,
    "save_count": 10,
    "has_audio": true,
    "audio_record_count": 4,
    "audio_play_count": 2
  },
  "suspicious_behaviors": [],
  "learning_strategy": {
    "strategy_type": "平衡型",
    "proficiency_score": 90
  },
  "metadata": {
    "student_id": "2024141460021_杨元广",
    "problem_id": "3Tree4",
    "analysis_time": "2026-01-12 12:30:08",
    "history_events_count": 53,
    "has_test_result_file": true
  },
  "ai_analysis": {
    "knowledge_points_analysis": [
      {
        "knowledge_point": "二叉树的中序遍历",
        "mastery_level": "精通",
        "mastery_score": 100,
        "is_weak": false,
        "evidence_from_history": [
          "学生实现了递归的中序遍历辅助函数 `inorderTraversalHelper`。",
          "所有测试用例均通过，表明中序遍历逻辑正确。"
        ],
        "specific_errors": [],
        "improvement_suggestions": []
      },
      {
        "knowledge_point": "表达式树的构建与表示",
        "mastery_level": "精通",
        "mastery_score": 100,
        "is_weak": false,
        "evidence_from_history": [
          "学生能够正确理解题目中给出的表达式树结构。",
          "能够根据测试用例中的 `vector<string>` 正确构建或理解树的结构。"
        ],
        "specific_errors": [],
        "improvement_suggestions": []
      },
      {
        "knowledge_point": "运算符优先级与结合性",
        "mastery_level": "精通",
        "mastery_score": 100,
        "is_weak": false,
        "evidence_from_history": [
          "学生实现了 `getPrecedence` 函数，正确区分了 `*`/`/` 和 `+`/`-` 的优先级。",
          "在 `inorderTraversalHelper` 函数中，根据 `parentPrecedence` 和 `isLeftChild` 的逻辑，正确地添加了括号。",
          "特别是对左结合性 (`isLeftChild` 为 true 时，`getPrecedence(node->val) < parentPrecedence`) 和非左结合性 (`getPrecedence(node->val) <= parentPrecedence`) 的处理，确保了表达式的正确性。",
          "所有测试用例均通过，包括了需要括号处理的复杂情况。"
        ],
        "specific_errors": [],
        "improvement_suggestions": []
      },
      {
        "knowledge_point": "递归函数设计与参数传递",
        "mastery_level": "精通",
        "mastery_score": 100,
        "is_weak": false,
        "evidence_from_history": [
          "学生成功设计了递归函数 `inorderTraversalHelper`。",
          "正确地传递了 `parentPrecedence` 和 `isLeftChild` 这两个关键参数，用于在递归调用中维护上下文信息。",
          "递归的终止条件 (`node == nullptr`) 也处理得当。"
        ],
        "specific_errors": [],
        "improvement_suggestions": []
      },
      {
        "knowledge_point": "字符串拼接与构建",
        "mastery_level": "精通",
        "mastery_score": 100,
        "is_weak": false,
        "evidence_from_history": [
          "学生在递归函数中通过字符串拼接 (`s1 + node->val + s2`) 来构建最终的中缀表达式。",
          "正确地在必要时将子表达式用括号包围 (`\"(\"+s1+node->val+s2+\")\"`)。"
        ],
        "specific_errors": [],
        "improvement_suggestions": []
      },
      {
        "knowledge_point": "空树/空节点处理",
        "mastery_level": "精通",
        "mastery_score": 100,
        "is_weak": false,
        "evidence_from_history": [
          "在 `toInfixExpression` 函数的开头，添加了 `if(root==nullptr) return \"\";` 来处理空树的情况。",
          "在 `inorderTraversalHelper` 函数的开头，添加了 `if(node==nullptr) return \"\";` 来处理空子节点的情况。",
          "测试用例中包含了空树的测试，并且通过了。"
        ],
        "specific_errors": [],
        "improvement_suggestions": []
      }
    ],
    "weak_knowledge_points_summary": [],
    "debugging_ability": {
      "score": 95,
      "level": "精通",
      "error_recognition_ability": "能够通过测试用例的失败（尽管本次没有出现失败）或观察代码逻辑来识别潜在问题。",
      "error_fixing_efficiency": "学生在第一次运行就通过了大部分测试，并在后续的几次运行和测试中快速定位并修复了空树处理的逻辑（虽然在最终代码中才体现）。",
      "debugging_strategy": "主要依赖于运行和测试用例驱动调试，能够根据测试结果快速调整代码逻辑。",
      "evidence_from_history": "学生在第一次运行后（timestamp=1764593993679）代码逻辑上存在问题（未处理空树），但后续的运行（timestamp=1764594015053, 1764594131910）和测试（timestamp=1764594016003, 1764594137095）显示其能够快速修正，并在最终版本中加入了空树处理。学生在代码演变中，在`toInfixExpression`函数开头添加了`if(root==nullptr) return \"\";`，这表明其在测试过程中发现了空树的边界情况并进行了修正。"
    },
    "code_evolution_analysis": {
      "total_iterations": 16,
      "improvement_pattern": "迭代优化型",
      "key_changes": [
        "初始版本 (timestamp=1764593978075): 实现了基本的中序遍历和优先级判断，但未处理空树情况。",
        "第一次运行/测试 (timestamp=1764593993679, 1764594007825): 发现空树处理问题（尽管没有明确的编译错误，但可能通过测试用例发现）。",
        "后续编辑与运行 (timestamp=1764594011406 - 1764594125417): 学生在 `toInfixExpression` 函数中添加了 `if(root==nullptr) return \"\";` 来处理空树。",
        "最终版本 (timestamp=1764594137062): 包含空树处理逻辑，并通过所有测试。"
      ],
      "learning_curve": "学生对核心逻辑（递归遍历、优先级、括号添加）掌握较好，主要是在边界条件（空树）的处理上进行了迭代优化。",
      "independence_assessment": "高独立性。学生从头开始实现了核心逻辑，并在测试反馈后独立完成了边界条件的补充。"
    },
    "code_quality": {
      "correctness": {
        "score": 100,
        "comment": "代码逻辑严谨，完全符合题目要求，并通过了所有测试用例。"
      },
      "time_complexity": {
        "actual": "O(N)",
        "optimal": "O(N)",
        "is_optimal": true,
        "comment": "中序遍历访问每个节点一次，时间复杂度为O(N)，其中N为树中的节点数。"
      },
      "space_complexity": {
        "actual": "O(H)",
        "optimal": "O(H)",
        "is_optimal": true,
        "comment": "递归调用的栈深度，最坏情况下为O(N)（链状树），最好情况下为O(log N)（平衡树）。H为树的高度。"
      },
      "readability": {
        "score": 85,
        "comment": "代码结构清晰，函数命名和变量命名（如 `parentPrecedence`, `isLeftChild`）具有描述性。缺少对辅助函数功能的详细注释，但整体可读性良好。"
      },
      "code_style": {
        "score": 80,
        "comment": "缩进和格式基本统一，使用了标准C++库。变量命名清晰，但可以考虑为辅助函数添加更详细的注释。"
      }
    },
    "learning_process_assessment": {
      "problem_solving_strategy": "测试驱动与迭代优化",
      "strategy_description": "学生首先实现了核心的递归遍历和优先级判断逻辑，然后通过运行和测试来验证，并根据测试结果（特别是边界条件）进行迭代优化。",
      "independence_level": "高",
      "independence_evidence": "学生从头开始编写了核心的递归函数和优先级判断逻辑，没有明显的粘贴痕迹。编辑历史显示了对代码逻辑的思考和调整，而非简单复制粘贴。",
      "time_management": "用时适中，操作间隔合理，表明在独立思考和调试。",
      "focus_level": "专注度较好，操作间隔正常，没有频繁的跳跃式操作。"
    },
    "overall_assessment": {
      "mastery_percentage": 98,
      "mastery_level": "精通",
      "grade_recommendation": "A",
      "confidence_level": "高",
      "confidence_reason": "学生代码逻辑完整，通过了所有测试用例，且操作历史显示了独立思考和解决问题的过程。",
      "readiness_for_next_topic": true,
      "readiness_reason": "学生在表达式树的中缀遍历、优先级处理、括号添加以及递归设计方面都表现出高水平的掌握，为学习更复杂的树相关问题打下了坚实基础。",
      "key_strengths": [
        "对递归算法的深刻理解和应用能力。",
        "准确处理运算符优先级和结合性，正确添加括号。",
        "良好的边界条件处理意识（空树）。",
        "独立解决问题的能力强。"
      ],
      "key_weaknesses": [
        "（几乎没有）在初始版本中遗漏了空树处理，但很快得到修正。"
      ],
      "priority_improvements": [
        "继续保持对递归和树结构的深入学习。",
        "在解决问题时，可以更早地考虑边界条件，以减少迭代次数。"
      ]
    },
    "metadata": {
      "analysis_timestamp": "2026-01-12 12:40:42",
      "has_complete_history": true,
      "history_event_count": 53,
      "analysis_quality": "深度分析"
    }
  }
}